gdrive_knife.py
gdrive_knife-1.0.7.dist-info/licenses/LICENSE
gdrive_knife-1.0.7.dist-info/METADATA
gdrive_knife-1.0.7.dist-info/WHEEL
gdrive_knife-1.0.7.dist-info/top_level.txt
gdrive_knife-1.0.7.dist-info/RECORD
