Metadata-Version: 2.4
Name: gdrive_knife
Version: 1.0.7
Author-email: Jakub Czajka <jakub@ekhem.eu.org>
Requires-Python: >=3.13.5
License-File: LICENSE
Requires-Dist: cryptography==43.0.0
Requires-Dist: google-api-python-client==2.187.0
Requires-Dist: google-auth-httplib2==0.2.1
Requires-Dist: google-auth-oauthlib==1.2.3
Dynamic: license-file
